liteyuki_plugin_aichat/__init__.py
liteyuki_plugin_aichat/chat_typing.py
liteyuki_plugin_aichat-0.0.0.dev5.dist-info/METADATA
liteyuki_plugin_aichat-0.0.0.dev5.dist-info/WHEEL
liteyuki_plugin_aichat-0.0.0.dev5.dist-info/RECORD
