Metadata-Version: 2.1
Name: liteyuki_plugin_aichat
Version: 0.0.0.dev5
Summary: 
Author: Expliyh
Author-email: expliyh@outlook.com
Requires-Python: >=3.12,<4.0
Classifier: Programming Language :: Python :: 3
Classifier: Programming Language :: Python :: 3.12
Classifier: Programming Language :: Python :: 3.13
Requires-Dist: asyncmy (>=0.2.9,<0.3.0)
Requires-Dist: asyncpg (>=0.30.0,<0.31.0)
Requires-Dist: nonebot-adapter-onebot (>=2.4.6,<3.0.0)
Requires-Dist: nonebot-adapter-satori (>=0.12.6,<0.13.0)
Requires-Dist: nonebot2 (>=2.4.0,<3.0.0)
Requires-Dist: sqlalchemy[asyncio] (>=2.0.36,<3.0.0)
